antsy/__init__.py
antsy/exceptions.py
antsy/common/__init__.py
antsy/common/models.py
antsy/namespaces/__init__.py
antsy/namespaces/appointments/__init__.py
antsy/namespaces/appointments/models.py
antsy/namespaces/auth/__init__.py
antsy/namespaces/auth/models.py
antsy/namespaces/customers/__init__.py
antsy/namespaces/customers/models.py
antsy/namespaces/sites/__init__.py
antsy/namespaces/sites/models.py
python_antsy-0.0.17.dist-info/LICENSE
python_antsy-0.0.17.dist-info/METADATA
python_antsy-0.0.17.dist-info/WHEEL
python_antsy-0.0.17.dist-info/top_level.txt
python_antsy-0.0.17.dist-info/RECORD
